stegosphere/__init__.py
stegosphere/config.py
stegosphere/io.py
stegosphere/utils.py
stegosphere/analysis/__init__.py
stegosphere/analysis/accuracy.py
stegosphere/analysis/analysis.py
stegosphere/analysis/capacity.py
stegosphere/analysis/detectability.py
stegosphere/analysis/efficiency.py
stegosphere/analysis/imperceptibility.py
stegosphere/analysis/robustness.py
stegosphere/analysis/visualizer.py
stegosphere/containers/__init__.py
stegosphere/containers/audio.py
stegosphere/containers/container.py
stegosphere/containers/image.py
stegosphere/containers/ttf.py
stegosphere/containers/video.py
stegosphere/methods/BPCS.py
stegosphere/methods/IWT.py
stegosphere/methods/LSB.py
stegosphere/methods/VD.py
stegosphere/methods/__init__.py
stegosphere/methods/ttf_CustomTable.py
stegosphere/methods/backend/LSB_c.c
stegosphere/methods/backend/lsb.so
stegosphere/tools/__init__.py
stegosphere/tools/compression.py
stegosphere/tools/crypt.py
stegosphere/tools/ecc.py
stegosphere/tools/multifile.py
stegosphere-1.2.2.dist-info/METADATA
stegosphere-1.2.2.dist-info/WHEEL
stegosphere-1.2.2.dist-info/top_level.txt
stegosphere-1.2.2.dist-info/RECORD
