Metadata-Version: 2.1
Name: stegosphere
Version: 1.2.2
Summary: A flexible steganography and steganalysis library supporting various file types, including encryption and compression
Home-page: https://github.com/Maximilian-Koch/stegosphere
Author: Maximilian Koch
License: GPL-3.0-or-later
Project-URL: Homepage, https://github.com/Maximilian-Koch/stegosphere
Project-URL: Repository, https://github.com/Maximilian-Koch/stegosphere
Requires-Python: >=3.6
Requires-Dist: numpy
